yuno/LICENSE
yuno/__init__.py
yuno/client.py
yuno/collection.py
yuno/cursor.py
yuno/database.py
yuno/direction.py
yuno/encoder.py
yuno/launcher.py
yuno/object.py
yuno/watch.py
yuno/objects/__init__.py
yuno/objects/dict.py
yuno/objects/list.py
yuno/security/__init__.py
yuno/security/encrypt.py
yuno/security/hash.py
yuno/security/token.py
yuno/utils/__init__.py
yuno/utils/annotations.py
yuno/utils/logging.py
yuno/utils/security.py
yuno/utils/string.py
yuno/utils/unpack.py
yuno-1.1.dist-info/LICENSE
yuno-1.1.dist-info/METADATA
yuno-1.1.dist-info/WHEEL
yuno-1.1.dist-info/top_level.txt
yuno-1.1.dist-info/RECORD
