Metadata-Version: 2.1
Name: yuno
Version: 1.1
Summary: Manipulate your databases as if you never leaved Python!
Home-page: https://github.com/Animenosekai/yuno
Author: Anime no Sekai
Author-email: niichannomail@gmail.com
License: MIT
Download-URL: https://github.com/Animenosekai/yuno/archive/v1.1.tar.gz
Keywords: python,yuno,database,database-management,mongo,mongodb,account,account-management,database-client,client,mongo-client
Platform: UNKNOWN
Classifier: Development Status :: 4 - Beta
Classifier: License :: OSI Approved :: MIT License
Classifier: Programming Language :: Python :: 3
Classifier: Programming Language :: Python :: 3.8
Classifier: Programming Language :: Python :: 3.9
Classifier: Programming Language :: Python :: 3.10
Requires-Python: >=3.8, <4
License-File: LICENSE
Requires-Dist: pymongo (>=3.11.3)
Requires-Dist: psutil (>=5.8.0)
Requires-Dist: PyYAML (>=6.0)
Requires-Dist: argon2-cffi (>=20.1.0)
Requires-Dist: pyjwt (>=2.0.1)
Requires-Dist: pycryptodome (>=3.10.1)
Requires-Dist: typing ; python_version < "3.8"
